{
    "activities": [
        {
            "name": "BinanceWallet is hosting an exclusive TGE for ParticleNtwrk, on PancakeSwap",
            "name_zh_CN": "BinanceWallet举办独家TGE ParticleNtwrk",
            "link": "https://www.binance.com/en/events/particle-tge-rules",
            "startDate": "2025-03-23",
            "endDate": "2025-03-26",
            "platform": "Binance"
        },
        {
            "name": "Bitget launch Nillion (NIL) pre-market trading on Mar 21, 12:00 PM (UTC).",
            "link": "https://www.bitget.com/support/articles/12560603824479",
            "startDate": "2025-03-21",
            "endDate": "2025-03-24",
            "platform": "Bitget"
        }
    ],
    "referral": [
        {
            "name": "Binance",
            "link": "https://accounts.binance.com/register?ref=10196687"
        },
        {
            "name": "Bitget",
            "link": "https://www.bitget.com/zh-CN/referral/register?clacCode=ALG0ZBV3&from=%2Fzh-CN%2Fevents%2Freferral-all-program&source=events&utmSource=PremierInviter"
        }
    ]
}